[{"mammal": "Blue whale", "weight": 136000}, {"mammal": "Bowhead", "weight": 100000}, {"mammal": "Fin whale", "weight": 70000}, {"mammal": "Southern right whale", "weight": 45000}, {"mammal": "Humpback whale", "weight": 30000}, {"mammal": "Gray whale", "weight": 28500}, {"mammal": "Northern right whale", "weight": 23000}, {"mammal": "Sei whale", "weight": 20000}, {"mammal": "Bryde's whale", "weight": 16000}, {"mammal": "Baird's beaked whale", "weight": 11380}, {"mammal": "Minke whale", "weight": 7500}, {"mammal": "Northern bottlenose whale", "weight": 6500}, {"mammal": "Gervais's beaked whale", "weight": 5600}, {"mammal": "African elephant", "weight": 4800}, {"mammal": "Killer whale", "weight": 3988}, {"mammal": "Hippopotamus", "weight": 3750}, {"mammal": "Asian elephant", "weight": 3178}, {"mammal": "Cuvier's beaked whale", "weight": 2701}, {"mammal": "Short-finned pilot whale", "weight": 2200}, {"mammal": "White rhinoceros", "weight": 2175}, {"mammal": "Javan rhinoceros", "weight": 1750}, {"mammal": "Indian rhinoceros", "weight": 1602}, {"mammal": "Northern elephant seal", "weight": 1600}, {"mammal": "Beluga", "weight": 1430}, {"mammal": "Southern elephant seal", "weight": 1400}, {"mammal": "Sumatran rhinoceros", "weight": 1260}, {"mammal": "Narwhal", "weight": 1250}, {"mammal": "Black rhinoceros", "weight": 1100}, {"mammal": "Blainville's beaked whale", "weight": 1088}, {"mammal": "Long-finned pilot whale", "weight": 1060}, {"mammal": "Walrus", "weight": 1013}, {"mammal": "Gaur", "weight": 825}, {"mammal": "Giraffe", "weight": 800}, {"mammal": "Kouprey", "weight": 800}, {"mammal": "False killer whale", "weight": 748}, {"mammal": "Water buffalo", "weight": 725}, {"mammal": "African buffalo", "weight": 700}, {"mammal": "Banteng", "weight": 700}, {"mammal": "Yak", "weight": 667}, {"mammal": "American bison", "weight": 630}, {"mammal": "European bison", "weight": 610}, {"mammal": "Amazonian manatee", "weight": 480}, {"mammal": "Polar bear", "weight": 475}, {"mammal": "Bactrian camel", "weight": 475}, {"mammal": "Weddell seal", "weight": 425}, {"mammal": "Risso's dolphin", "weight": 425}, {"mammal": "Pygmy sperm whale", "weight": 425}, {"mammal": "Northern sea lion", "weight": 415}, {"mammal": "Hooded seal", "weight": 405}, {"mammal": "Moose", "weight": 386}, {"mammal": "Grevy's zebra", "weight": 384}, {"mammal": "Bearded seal", "weight": 373}, {"mammal": "Leopard seal", "weight": 368}, {"mammal": "Dugong", "weight": 360}, {"mammal": "Caribbean manatee", "weight": 322}, {"mammal": "Muskox", "weight": 315}, {"mammal": "Bongo", "weight": 308}, {"mammal": "Baird's tapir", "weight": 300}, {"mammal": "Mountain zebra", "weight": 296}, {"mammal": "Burchell's zebra", "weight": 280}, {"mammal": "Indo-Pacific humpbacked dolphin", "weight": 280}, {"mammal": "Brown bear and grizzly bear", "weight": 278}, {"mammal": "Kiang", "weight": 275}, {"mammal": "Mediterranean monk seal", "weight": 275}, {"mammal": "Gray seal", "weight": 268}, {"mammal": "Brazilian tapir", "weight": 250}, {"mammal": "Malayan tapir", "weight": 250}, {"mammal": "Tamaraw", "weight": 240}, {"mammal": "Kulan", "weight": 230}, {"mammal": "Roan antelope", "weight": 225}, {"mammal": "Sable antelope", "weight": 225}, {"mammal": "Okapi", "weight": 225}, {"mammal": "Hawaiian monk seal", "weight": 223}, {"mammal": "Greater kudu", "weight": 218}, {"mammal": "Pygmy hippopotamus", "weight": 215}, {"mammal": "Atlantic white-sided dolphin", "weight": 208}, {"mammal": "Southern sea lion", "weight": 208}, {"mammal": "Melon-headed whale", "weight": 206}, {"mammal": "Giant forest hog", "weight": 203}, {"mammal": "Bottlenosed dolphin", "weight": 200}, {"mammal": "Red deer", "weight": 200}, {"mammal": "Irrawaddy dolphin", "weight": 190}, {"mammal": "Australian sea lion", "weight": 190}, {"mammal": "New Zealand sea lion", "weight": 188}, {"mammal": "Pere David's deer", "weight": 187}, {"mammal": "Sambar", "weight": 185}, {"mammal": "Takin", "weight": 180}, {"mammal": "Harp seal", "weight": 180}, {"mammal": "California sea lion", "weight": 180}, {"mammal": "Wild boar", "weight": 180}, {"mammal": "Nilgai", "weight": 180}, {"mammal": "Scimitar-horned oryx", "weight": 178}, {"mammal": "Ross seal", "weight": 177}, {"mammal": "Waterbuck", "weight": 175}, {"mammal": "Lion", "weight": 175}, {"mammal": "Gemsbok", "weight": 170}, {"mammal": "Barasingha", "weight": 170}, {"mammal": "Northern fur seal", "weight": 166}, {"mammal": "Blue wildebeest", "weight": 165}, {"mammal": "Fraser's dolphin", "weight": 164}, {"mammal": "Argali", "weight": 160}, {"mammal": "Hartebeest", "weight": 159}, {"mammal": "Anoa", "weight": 155}, {"mammal": "American black bear", "weight": 154}, {"mammal": "Mountain anoa", "weight": 150}, {"mammal": "Mountain tapir", "weight": 149}, {"mammal": "Gorilla", "weight": 140}, {"mammal": "Thorold's deer", "weight": 135}, {"mammal": "Black wildebeest", "weight": 132}, {"mammal": "South African fur seal", "weight": 128}, {"mammal": "Guanaco", "weight": 128}, {"mammal": "Eld's deer", "weight": 123}, {"mammal": "Arabian oryx", "weight": 121}, {"mammal": "Nyala", "weight": 120}, {"mammal": "Dall's porpoise", "weight": 120}, {"mammal": "Tiger", "weight": 120}, {"mammal": "Giant panda", "weight": 118}, {"mammal": "Harbor seal", "weight": 115}, {"mammal": "Rough-toothed dolphin", "weight": 114}, {"mammal": "Pantropical spotted dolphin", "weight": 113}, {"mammal": "Striped dolphin", "weight": 113}, {"mammal": "South American fur seal", "weight": 110}, {"mammal": "Topi", "weight": 110}, {"mammal": "Spectacled bear", "weight": 109}, {"mammal": "Kob", "weight": 105}, {"mammal": "Asiatic black bear", "weight": 104}, {"mammal": "Pacific white-sided dolphin", "weight": 103}, {"mammal": "Bearded pig", "weight": 103}, {"mammal": "Marsh deer", "weight": 103}, {"mammal": "Caribou and reindeer", "weight": 101}, {"mammal": "Wart hog", "weight": 100}, {"mammal": "Sloth bear", "weight": 100}, {"mammal": "Lechwe", "weight": 95}, {"mammal": "Aoudad", "weight": 93}, {"mammal": "Addax", "weight": 93}, {"mammal": "Mountain goat", "weight": 90}, {"mammal": "Nile lechwe", "weight": 90}, {"mammal": "Ringed seal", "weight": 90}, {"mammal": "Baikal seal", "weight": 90}, {"mammal": "Ribbon seal", "weight": 90}, {"mammal": "Red river hog", "weight": 88}, {"mammal": "Bushpig", "weight": 88}, {"mammal": "Sitatunga", "weight": 88}, {"mammal": "White-tailed deer", "weight": 87}, {"mammal": "Caspian seal", "weight": 86}, {"mammal": "Spotted seal", "weight": 85}, {"mammal": "Antarctic fur seal", "weight": 85}, {"mammal": "Sassaby or blesbok", "weight": 85}, {"mammal": "Amazon dolphin", "weight": 84}, {"mammal": "Yangzte river dolphin or baiji", "weight": 84}, {"mammal": "Lesser kudu", "weight": 83}, {"mammal": "Ibex", "weight": 83}, {"mammal": "Jaguar", "weight": 81}, {"mammal": "Short-beaked saddleback dolphin", "weight": 80}, {"mammal": "Javan pig", "weight": 76}, {"mammal": "Nilgiri tahr", "weight": 75}, {"mammal": "Dall's sheep", "weight": 73}, {"mammal": "Dama gazelle", "weight": 73}, {"mammal": "Babirusa", "weight": 72}, {"mammal": "Bighorn sheep", "weight": 70}, {"mammal": "Jentink's duiker", "weight": 70}, {"mammal": "Chilean guemal", "weight": 70}, {"mammal": "West Caucasian tur", "weight": 70}, {"mammal": "Ganges dolphin", "weight": 70}, {"mammal": "Fallow deer", "weight": 70}, {"mammal": "Grant's gazelle", "weight": 67}, {"mammal": "Orangutan", "weight": 64}, {"mammal": "Timor deer", "weight": 63}, {"mammal": "Cougar", "weight": 63}, {"mammal": "Spotted hyena", "weight": 63}, {"mammal": "Yellow-backed duiker", "weight": 62}, {"mammal": "Bushbuck", "weight": 60}, {"mammal": "Aardvark", "weight": 60}, {"mammal": "Southern reedbuck", "weight": 58}, {"mammal": "Spanish ibex", "weight": 58}, {"mammal": "Mule deer", "weight": 57}, {"mammal": "Hector's dolphin", "weight": 56}, {"mammal": "Red kangaroo", "weight": 55}, {"mammal": "Bawean deer", "weight": 55}, {"mammal": "Bharal", "weight": 55}, {"mammal": "Capybara", "weight": 55}, {"mammal": "New Zealand fur seal", "weight": 55}, {"mammal": "Leopard", "weight": 54}, {"mammal": "Cheetah", "weight": 54}, {"mammal": "Harbor porpoise", "weight": 53}, {"mammal": "Impala", "weight": 53}, {"mammal": "Vicugna", "weight": 50}, {"mammal": "Sub-Antarctic fur seal", "weight": 50}, {"mammal": "Philippine brown deer", "weight": 50}, {"mammal": "Commerson's dolphin", "weight": 50}, {"mammal": "Snow leopard", "weight": 50}, {"mammal": "East Caucasian tur", "weight": 50}, {"mammal": "Antilopine wallaroo", "weight": 50}, {"mammal": "Eastern gray kangaroo", "weight": 50}, {"mammal": "Soemmering's gazelle", "weight": 49}, {"mammal": "Goitered gazelle", "weight": 49}, {"mammal": "Rhim gazelle", "weight": 49}, {"mammal": "River dolphin", "weight": 47}, {"mammal": "Nubian ibex", "weight": 46}, {"mammal": "Pronghorn", "weight": 46}, {"mammal": "Sun bear", "weight": 46}, {"mammal": "Bohar reedbuck", "weight": 46}, {"mammal": "Southern fur seal", "weight": 46}, {"mammal": "Red brocket", "weight": 46}, {"mammal": "Guemals", "weight": 45}, {"mammal": "Chimpanzee", "weight": 45}, {"mammal": "Gerenuk", "weight": 44}, {"mammal": "Brown hyena", "weight": 42}, {"mammal": "Sika deer", "weight": 42}, {"mammal": "Markhor", "weight": 41}, {"mammal": "Calamian deer", "weight": 41}, {"mammal": "Franciscana", "weight": 41}, {"mammal": "Striped hyena", "weight": 40}, {"mammal": "Pygmy chimpanzee or bonono", "weight": 40}, {"mammal": "Eastern roe deer", "weight": 39}, {"mammal": "Springbok", "weight": 39}, {"mammal": "Blackbuck", "weight": 38}, {"mammal": "Saiga", "weight": 38}, {"mammal": "Chamois", "weight": 38}, {"mammal": "Chital", "weight": 36}, {"mammal": "Himalayan tahr", "weight": 35}, {"mammal": "Chacoan peccary", "weight": 35}, {"mammal": "Tufted deer", "weight": 34}, {"mammal": "Giant armadillo", "weight": 33}, {"mammal": "Finless porpoise", "weight": 33}, {"mammal": "Pampas deer", "weight": 33}, {"mammal": "Goral", "weight": 32}, {"mammal": "Northern hairy-nosed wombat", "weight": 31}, {"mammal": "Dibatag", "weight": 31}, {"mammal": "Wallaroo", "weight": 30}, {"mammal": "Pyranean chamois", "weight": 30}, {"mammal": "Mountain reedbuck", "weight": 30}, {"mammal": "Mongolian gazelle", "weight": 30}, {"mammal": "Giant anteater", "weight": 29}, {"mammal": "Western gray kangaroo", "weight": 28}, {"mammal": "Chinese goral", "weight": 27}, {"mammal": "Gray wolf", "weight": 27}, {"mammal": "African wild dog", "weight": 27}, {"mammal": "Sea otter", "weight": 26}, {"mammal": "Coarse-haired wombat", "weight": 26}, {"mammal": "Hairy-nosed wombat", "weight": 26}, {"mammal": "Thomson's gazelle", "weight": 25}, {"mammal": "Common rhebok", "weight": 25}, {"mammal": "European beaver", "weight": 25}, {"mammal": "Giant otter", "weight": 24}, {"mammal": "Cape porcupine", "weight": 24}, {"mammal": "African clawless otter", "weight": 24}, {"mammal": "Mountain gazelle", "weight": 23}, {"mammal": "Arabian tahr", "weight": 23}, {"mammal": "Mandrill", "weight": 23}, {"mammal": "Lynx", "weight": 23}, {"mammal": "White-lipped peccary", "weight": 22}, {"mammal": "Fea's muntjac", "weight": 22}, {"mammal": "Western roe deer", "weight": 22}, {"mammal": "Maned wolf", "weight": 22}, {"mammal": "Indian muntjac", "weight": 21}, {"mammal": "American beaver", "weight": 20}, {"mammal": "Collared peccary", "weight": 20}, {"mammal": "Indian crested porcupine", "weight": 20}, {"mammal": "African porcupine", "weight": 20}, {"mammal": "Speke's gazelle", "weight": 20}, {"mammal": "Clouded leopard", "weight": 20}, {"mammal": "Four-horned antelope", "weight": 19}, {"mammal": "Indian gazelle", "weight": 19}, {"mammal": "Bush duiker", "weight": 19}, {"mammal": "Drill", "weight": 18}, {"mammal": "Black duiker", "weight": 18}, {"mammal": "Reeves's muntjac", "weight": 18}, {"mammal": "Hamadryas baboon", "weight": 18}, {"mammal": "Black wallaroo", "weight": 18}, {"mammal": "Zebra duiker", "weight": 18}, {"mammal": "Cuvier's gazelle", "weight": 18}, {"mammal": "Oribi", "weight": 17}, {"mammal": "Gray brocket", "weight": 17}, {"mammal": "Whiptail wallaby", "weight": 17}, {"mammal": "Wolverine", "weight": 16}, {"mammal": "Gelada baboon", "weight": 16}, {"mammal": "Red-necked wallaby", "weight": 16}, {"mammal": "Agile wallaby", "weight": 16}, {"mammal": "Caracal", "weight": 16}, {"mammal": "Dhole", "weight": 16}, {"mammal": "Red-fronted gazelle", "weight": 15}, {"mammal": "Swamp wallaby", "weight": 15}, {"mammal": "Proboscis monkey", "weight": 15}, {"mammal": "Dorcas gazelle", "weight": 15}, {"mammal": "Black-fronted duiker", "weight": 14}, {"mammal": "African civet", "weight": 14}, {"mammal": "Hanuman langur", "weight": 14}, {"mammal": "Asiatic golden cat", "weight": 14}, {"mammal": "Serval", "weight": 13}, {"mammal": "Coyote", "weight": 13}, {"mammal": "Indian pangolin", "weight": 13}, {"mammal": "Steenbok", "weight": 13}, {"mammal": "Old World badger", "weight": 13}, {"mammal": "Red-flanked duiker", "weight": 13}, {"mammal": "Patagonian cavy", "weight": 13}, {"mammal": "Pacarana", "weight": 12}, {"mammal": "Binturong", "weight": 12}, {"mammal": "Chinese forest musk deer", "weight": 12}, {"mammal": "Klipspringer", "weight": 12}, {"mammal": "Tonkean macaque", "weight": 12}, {"mammal": "Bay duiker", "weight": 12}, {"mammal": "Chinese water deer", "weight": 12}, {"mammal": "Capped leaf monkey", "weight": 11}, {"mammal": "Grizzled tree kangaroo", "weight": 11}, {"mammal": "Black-striped scrub wallaby", "weight": 11}, {"mammal": "Woolly spider monkey or muriqui", "weight": 11}, {"mammal": "Spanish lynx", "weight": 11}, {"mammal": "Alpine musk deer", "weight": 11}, {"mammal": "Water chevrotain", "weight": 11}, {"mammal": "Golden jackal", "weight": 11}, {"mammal": "Barbary macaque", "weight": 11}, {"mammal": "African golden cat", "weight": 11}, {"mammal": "Fishing cat", "weight": 11}, {"mammal": "Hog badger", "weight": 11}, {"mammal": "Tibetan macaque", "weight": 10}, {"mammal": "Black-backed jackal", "weight": 10}, {"mammal": "Side-striped jackal", "weight": 10}, {"mammal": "Cape grysbok", "weight": 10}, {"mammal": "Canada lynx", "weight": 10}, {"mammal": "Oriental civet", "weight": 10}, {"mammal": "Jungle cat", "weight": 10}, {"mammal": "Honey badger", "weight": 10}, {"mammal": "Southern pudu", "weight": 10}, {"mammal": "Siberian musk deer", "weight": 10}, {"mammal": "Natal duiker", "weight": 10}, {"mammal": "Guereza", "weight": 10}, {"mammal": "Douc langur", "weight": 10}, {"mammal": "Doria's tree kangaroo", "weight": 10}, {"mammal": "King colobus", "weight": 10}, {"mammal": "Fossa", "weight": 10}, {"mammal": "Small-eared dog", "weight": 10}, {"mammal": "Red-capped mangabey", "weight": 9}, {"mammal": "Tana River mangabey", "weight": 9}, {"mammal": "Gray-cheeked mangabey", "weight": 9}, {"mammal": "Bennett's tree kangaroo", "weight": 9}, {"mammal": "Koala", "weight": 9}, {"mammal": "Stump-tailed macaque", "weight": 9}, {"mammal": "Assam macaque", "weight": 9}, {"mammal": "Mountain paca", "weight": 9}, {"mammal": "Northern river otter", "weight": 9}, {"mammal": "Blue monkey", "weight": 9}, {"mammal": "Paca", "weight": 9}, {"mammal": "Smooth-coated otter", "weight": 9}, {"mammal": "Japanese macaque", "weight": 9}, {"mammal": "Ocelot", "weight": 9}, {"mammal": "Angolan colobus", "weight": 9}, {"mammal": "Bobcat", "weight": 9}, {"mammal": "North American porcupine", "weight": 9}, {"mammal": "Rhesus monkey", "weight": 8}, {"mammal": "Golden leaf monkey", "weight": 8}, {"mammal": "Pygmy hog", "weight": 8}, {"mammal": "Black tree kangaroo", "weight": 8}, {"mammal": "American badger", "weight": 8}, {"mammal": "Old World porcupine", "weight": 8}, {"mammal": "Celebes crested macaque", "weight": 8}, {"mammal": "Pigtail macaque", "weight": 8}, {"mammal": "Black spider monkey", "weight": 8}, {"mammal": "Liontail macaque", "weight": 8}, {"mammal": "Nutria", "weight": 8}, {"mammal": "Patas monkey", "weight": 8}, {"mammal": "White-bellied spider monkey", "weight": 8}, {"mammal": "Neotropical river otter", "weight": 8}, {"mammal": "Long-nosed echidna", "weight": 8}, {"mammal": "Goodfellow's tree kangaroo", "weight": 7}, {"mammal": "Tangalunga", "weight": 7}, {"mammal": "Francois' langur", "weight": 7}, {"mammal": "Bobak marmot", "weight": 7}, {"mammal": "Central American spider monkey", "weight": 7}, {"mammal": "Matschie's tree kangaroo", "weight": 7}, {"mammal": "Purple-faced leaf monkey", "weight": 7}, {"mammal": "Dusky leaf monkey", "weight": 7}, {"mammal": "Mantled howler monkey", "weight": 7}, {"mammal": "Maxwell's duiker", "weight": 7}, {"mammal": "Bear cuscus", "weight": 7}, {"mammal": "Mexican black howler monkey", "weight": 7}, {"mammal": "White-handed gibbon", "weight": 7}, {"mammal": "Bonnet macaque", "weight": 7}, {"mammal": "Flat-headed cat", "weight": 7}, {"mammal": "Eurasian river otter", "weight": 7}, {"mammal": "Grizzled leaf monkey", "weight": 7}, {"mammal": "North Sumatran leaf monkey", "weight": 7}, {"mammal": "Bolivian red howler monkey", "weight": 7}, {"mammal": "Cane rat", "weight": 7}, {"mammal": "Red howler monkey", "weight": 7}, {"mammal": "Mitred leaf monkey", "weight": 7}, {"mammal": "Tasmanian devil", "weight": 7}, {"mammal": "Raccoon dog", "weight": 7}, {"mammal": "Crab-eating fox", "weight": 7}, {"mammal": "Tammar wallaby", "weight": 7}, {"mammal": "Suni", "weight": 7}, {"mammal": "Greater mouse-deer", "weight": 7}, {"mammal": "Long-tailed macaque", "weight": 6}, {"mammal": "Hoary marmot", "weight": 6}, {"mammal": "Crab-eating raccoon", "weight": 6}, {"mammal": "Hoffmann's two-toed sloth", "weight": 6}, {"mammal": "Blue duiker", "weight": 6}, {"mammal": "Linne's two-toed sloth", "weight": 6}, {"mammal": "Silvery gibbon", "weight": 6}, {"mammal": "Bush dog", "weight": 6}, {"mammal": "Ringtailed rock wallaby", "weight": 6}, {"mammal": "White-whiskered spider monkey", "weight": 6}, {"mammal": "Chamek spider monkey", "weight": 6}, {"mammal": "Plains viscacha", "weight": 6}, {"mammal": "Common raccoon", "weight": 6}, {"mammal": "Brush-tailed rock wallaby", "weight": 6}, {"mammal": "De Brazza's monkey", "weight": 6}, {"mammal": "Agile gibbon", "weight": 6}, {"mammal": "Kloss's gibbon", "weight": 6}, {"mammal": "Northern nail-tailed wallaby", "weight": 6}, {"mammal": "Borneo gibbon", "weight": 6}, {"mammal": "Pileated gibbon", "weight": 6}, {"mammal": "Diademed sifaka", "weight": 6}, {"mammal": "Australian tiger cat", "weight": 6}, {"mammal": "Ridled nail-tailed wallaby", "weight": 6}, {"mammal": "Common long-nosed armadillo", "weight": 6}, {"mammal": "Wild cat", "weight": 6}, {"mammal": "White-nosed guenon", "weight": 5}, {"mammal": "Black howler monkey", "weight": 5}, {"mammal": "Sun-tailed monkey", "weight": 5}, {"mammal": "Preuss's monkey", "weight": 5}, {"mammal": "Tasmanian red-bellied pademelon", "weight": 5}, {"mammal": "Kirk's dik-dik", "weight": 5}, {"mammal": "Brown dorcopsis", "weight": 5}, {"mammal": "Leopard cat", "weight": 5}, {"mammal": "Verreaux's sifaka", "weight": 5}, {"mammal": "Six-banded armadillo", "weight": 5}, {"mammal": "Gray fox", "weight": 5}, {"mammal": "Coatimundi", "weight": 5}, {"mammal": "Vancouver marmot", "weight": 5}, {"mammal": "Allen's swamp monkey", "weight": 5}, {"mammal": "L'hoest's monkey", "weight": 5}, {"mammal": "Cuban hutia", "weight": 5}, {"mammal": "Diana monkey", "weight": 5}, {"mammal": "Gunther's dik-dik", "weight": 5}, {"mammal": "Tayra", "weight": 5}, {"mammal": "Mona monkey", "weight": 5}, {"mammal": "Northern tamandua", "weight": 5}, {"mammal": "Southern tamandua", "weight": 5}, {"mammal": "Owl-faced monkey", "weight": 4}, {"mammal": "Toque macaque", "weight": 4}, {"mammal": "Lesser panda", "weight": 4}, {"mammal": "Masked palm civet", "weight": 4}, {"mammal": "Allied rock wallaby", "weight": 4}, {"mammal": "Parma wallaby", "weight": 4}, {"mammal": "Three-toed tree sloth", "weight": 4}, {"mammal": "Black-footed rock wallaby", "weight": 4}, {"mammal": "European hare", "weight": 4}, {"mammal": "Black-tailed jack rabbit", "weight": 4}, {"mammal": "Mountain hare", "weight": 4}, {"mammal": "Bat-eared fox", "weight": 4}, {"mammal": "Red fox", "weight": 4}, {"mammal": "Red-legged pademelon", "weight": 4}, {"mammal": "Otter civet", "weight": 4}, {"mammal": "Cape fox", "weight": 4}, {"mammal": "Woodchuck", "weight": 4}, {"mammal": "Booted macaque", "weight": 4}, {"mammal": "Prehensile-tailed porcupine", "weight": 4}, {"mammal": "Maned sloth", "weight": 4}, {"mammal": "Lesser mouse-deer", "weight": 4}, {"mammal": "Red-necked pademelon", "weight": 4}, {"mammal": "White-nosed coati", "weight": 4}, {"mammal": "Black-cheeked white-nosed monkey", "weight": 4}, {"mammal": "Western rock wallaby", "weight": 4}, {"mammal": "Ruffed lemur", "weight": 4}, {"mammal": "Margay", "weight": 4}, {"mammal": "Lesser white-nosed monkey", "weight": 4}, {"mammal": "Rock hyrax", "weight": 4}, {"mammal": "Campbell's monkey", "weight": 4}, {"mammal": "Moustached monkey", "weight": 4}, {"mammal": "Crowned guenon", "weight": 4}, {"mammal": "Gray dorcopsis", "weight": 4}, {"mammal": "Golden-crowned sifaka", "weight": 4}, {"mammal": "Spotted cuscus", "weight": 4}, {"mammal": "Alpine marmot", "weight": 4}, {"mammal": "Striped skunk", "weight": 4}, {"mammal": "Marbled cat", "weight": 4}, {"mammal": "White-tailed mongoose", "weight": 4}, {"mammal": "Yellow-bellied marmot", "weight": 4}, {"mammal": "Quokka", "weight": 4}, {"mammal": "Sooty agouti", "weight": 4}, {"mammal": "Springhare", "weight": 4}, {"mammal": "Southern naked-tailed armadillo", "weight": 4}, {"mammal": "Molina's hog-nosed skunk", "weight": 3}, {"mammal": "Marsh mongoose", "weight": 3}, {"mammal": "Agouti", "weight": 3}, {"mammal": "Red-bellied monkey", "weight": 3}, {"mammal": "Owston's palm civet", "weight": 3}, {"mammal": "Rufous 'rat'-kangaroo", "weight": 3}, {"mammal": "Fisher", "weight": 3}, {"mammal": "Red uakari", "weight": 3}, {"mammal": "Mountain brush-tailed possum", "weight": 3}, {"mammal": "Brown lemur", "weight": 3}, {"mammal": "Common palm civet", "weight": 3}, {"mammal": "White-tailed jackrabbit", "weight": 3}, {"mammal": "Spectacled hare-wallaby", "weight": 3}, {"mammal": "Large bamboo rat", "weight": 3}, {"mammal": "Small Indian civet", "weight": 3}, {"mammal": "Long-snouted mongoose", "weight": 3}, {"mammal": "Kinkajou", "weight": 3}, {"mammal": "Oriental small-clawed otter", "weight": 3}, {"mammal": "Virginia opossum", "weight": 3}, {"mammal": "Tree hyrax", "weight": 3}, {"mammal": "Papuan mountain wallaby", "weight": 3}, {"mammal": "Brown-bearded saki", "weight": 3}, {"mammal": "Black uakari", "weight": 3}, {"mammal": "White-nosed bearded saki", "weight": 3}, {"mammal": "Hairy-rumpted agouti", "weight": 3}, {"mammal": "Pale fox", "weight": 3}, {"mammal": "Sand cat", "weight": 3}, {"mammal": "Northern naked-tailed armadillo", "weight": 3}, {"mammal": "Brush-tailed porcupine", "weight": 3}, {"mammal": "Indonesian porcupine", "weight": 3}, {"mammal": "Mexican agouti", "weight": 3}, {"mammal": "Corsac fox", "weight": 3}, {"mammal": "White-faced capuchin", "weight": 3}, {"mammal": "Azara's agouti", "weight": 3}, {"mammal": "Guyanan agouti", "weight": 3}, {"mammal": "Brown capuchin", "weight": 3}, {"mammal": "Ring-tailed lemur", "weight": 3}, {"mammal": "Weeping capuchin", "weight": 3}, {"mammal": "Gray cuscus", "weight": 3}, {"mammal": "Crowned lemur", "weight": 3}, {"mammal": "Yellow-throated marten", "weight": 3}, {"mammal": "Black lemur", "weight": 3}, {"mammal": "White-fronted capuchin", "weight": 2}, {"mammal": "Bush hyrax", "weight": 2}, {"mammal": "Indian spotted chevrotain", "weight": 2}, {"mammal": "Ground cuscus", "weight": 2}, {"mammal": "Swift fox", "weight": 2}, {"mammal": "Banded palm civet", "weight": 2}, {"mammal": "Brush-tailed possum", "weight": 2}, {"mammal": "Indian fox", "weight": 2}, {"mammal": "Cape hare", "weight": 2}, {"mammal": "Chinese pangolin", "weight": 2}, {"mammal": "Grison", "weight": 2}, {"mammal": "Aye-aye", "weight": 2}, {"mammal": "Small-toothed palm civet", "weight": 2}, {"mammal": "Striped-necked mongoose", "weight": 2}, {"mammal": "Royal antelope", "weight": 2}, {"mammal": "Little spotted cat", "weight": 2}, {"mammal": "Panther genet", "weight": 2}, {"mammal": "Mongoose", "weight": 2}, {"mammal": "Andean hairy armadillo", "weight": 2}, {"mammal": "Central American agouti", "weight": 2}, {"mammal": "Black-footed cat", "weight": 2}, {"mammal": "Banded hare-wallaby", "weight": 2}, {"mammal": "Mongoose lemur", "weight": 2}, {"mammal": "Kit fox", "weight": 2}, {"mammal": "Hairy armadillo", "weight": 2}, {"mammal": "Asian long-tailed porcupine", "weight": 2}, {"mammal": "Black giant squirrel", "weight": 2}, {"mammal": "Mexican tree porcupine", "weight": 2}, {"mammal": "Indian giant squirrel", "weight": 2}, {"mammal": "Black-legged mongoose", "weight": 2}, {"mammal": "Burmese ferret badger", "weight": 2}, {"mammal": "Asiatic brush-tailed porcupine", "weight": 2}, {"mammal": "African palm civet", "weight": 2}, {"mammal": "Hog-nosed skunk", "weight": 2}, {"mammal": "Island gray fox", "weight": 2}, {"mammal": "Small-spotted genet", "weight": 2}, {"mammal": "Crab-eating mongoose", "weight": 2}, {"mammal": "Large-spotted genet", "weight": 2}, {"mammal": "Old World rabbit", "weight": 2}, {"mammal": "Hodgson's giant flying squirrel", "weight": 2}, {"mammal": "Monk saki", "weight": 2}, {"mammal": "Red-bellied lemur", "weight": 2}, {"mammal": "Slender-tailed cloud rat", "weight": 2}, {"mammal": "Red giant flying squirrel", "weight": 2}, {"mammal": "Hairy tree porcupine", "weight": 2}, {"mammal": "Greater bamboo lemur", "weight": 2}, {"mammal": "Tasmanian bettong", "weight": 2}, {"mammal": "Ruddy mongoose", "weight": 2}, {"mammal": "Beech marten", "weight": 2}, {"mammal": "Red and white giant flying squirrel", "weight": 2}, {"mammal": "Scaly-tailed possum", "weight": 2}, {"mammal": "Indian giant flying squirrel", "weight": 2}, {"mammal": "Japanese giant flying squirrel", "weight": 2}, {"mammal": "Long-footed potoroo", "weight": 2}, {"mammal": "Abyssinian genet", "weight": 2}, {"mammal": "Brindled bandicoot", "weight": 2}, {"mammal": "Snowshoe rabbit", "weight": 2}, {"mammal": "Short-nosed echidna", "weight": 2}, {"mammal": "Malagasy civet", "weight": 2}, {"mammal": "Mountain viscacha", "weight": 2}, {"mammal": "Southern opossum", "weight": 2}, {"mammal": "Pichi", "weight": 2}, {"mammal": "La Plata three-banded armadillo", "weight": 2}, {"mammal": "Woylie", "weight": 2}, {"mammal": "Brown's hutia", "weight": 2}, {"mammal": "Gambian rat", "weight": 2}, {"mammal": "Guianan saki", "weight": 1}, {"mammal": "Seven-banded armadillo", "weight": 1}, {"mammal": "Golden bamboo lemur", "weight": 1}, {"mammal": "Potoroo", "weight": 1}, {"mammal": "Short-tailed mongoose", "weight": 1}, {"mammal": "Talapoin", "weight": 1}, {"mammal": "Muskrat", "weight": 1}, {"mammal": "Rusty-spotted cat", "weight": 1}, {"mammal": "Greater gliding possum", "weight": 1}, {"mammal": "Bamboo lemur", "weight": 1}, {"mammal": "Banded mongoose", "weight": 1}, {"mammal": "Rufous hare-wallaby", "weight": 1}, {"mammal": "Flying lemur (glider)", "weight": 1}, {"mammal": "Burrowing bettong", "weight": 1}, {"mammal": "Giant rat", "weight": 1}, {"mammal": "European pine marten", "weight": 1}, {"mammal": "Rabbit-bandicoot or bilby", "weight": 1}, {"mammal": "Small-eared galago", "weight": 1}, {"mammal": "Hispaniolan hutia", "weight": 1}, {"mammal": "Fennec", "weight": 1}, {"mammal": "Riverine or bushman rabbit", "weight": 1}, {"mammal": "Malagasy giant rat", "weight": 1}, {"mammal": "Duck-billed platypus", "weight": 1}, {"mammal": "Moonrat", "weight": 1}, {"mammal": "Peruvian mountain viscacha", "weight": 1}, {"mammal": "Rufous spiny bandicoot", "weight": 1}, {"mammal": "Nabarlek", "weight": 1}, {"mammal": "Southern bushy-tailed olingo", "weight": 1}, {"mammal": "Olingo", "weight": 1}, {"mammal": "Marsh cottontail rabbit", "weight": 1}, {"mammal": "Potto", "weight": 1}, {"mammal": "Gray monk saki", "weight": 1}, {"mammal": "Three-banded armadillo", "weight": 1}, {"mammal": "Northern bettong", "weight": 1}, {"mammal": "Equatorial saki", "weight": 1}, {"mammal": "Pale giant squirrel", "weight": 1}, {"mammal": "Indian flying fox", "weight": 1}, {"mammal": "Eastern cottontail", "weight": 1}, {"mammal": "Black-tailed prairie dog", "weight": 1}, {"mammal": "Mountain beaver", "weight": 1}, {"mammal": "Coppery titi", "weight": 1}, {"mammal": "Greater galago", "weight": 1}, {"mammal": "Quoll", "weight": 1}, {"mammal": "Sable", "weight": 1}, {"mammal": "Servaline genet", "weight": 1}, {"mammal": "Lemuroid ringtail possum", "weight": 1}, {"mammal": "Black-footed ferret", "weight": 1}, {"mammal": "Ringtail", "weight": 1}, {"mammal": "Haitian solenodon", "weight": 1}, {"mammal": "Japanese marten", "weight": 1}, {"mammal": "Blanford's fox", "weight": 1}, {"mammal": "Cuban solenodon", "weight": 1}, {"mammal": "Little grison", "weight": 1}, {"mammal": "Hooded skunk", "weight": 1}, {"mammal": "Rock cavy", "weight": 1}, {"mammal": "South American squirrel monkey", "weight": 1}, {"mammal": "Striped polecat, zorilla", "weight": 1}, {"mammal": "White-eared opossum", "weight": 1}, {"mammal": "New England cottontail rabbit", "weight": 1}, {"mammal": "Cacomistle", "weight": 1}, {"mammal": "Tenrec", "weight": 1}, {"mammal": "Black-footed tree rat", "weight": 1}, {"mammal": "Audubon's cottontail rabbit", "weight": 1}, {"mammal": "Gunnison's prairie dog", "weight": 1}, {"mammal": "Slow loris", "weight": 1}, {"mammal": "Western quoll", "weight": 1}, {"mammal": "American marten", "weight": 1}, {"mammal": "Lemurine night monkey", "weight": 1}, {"mammal": "Noisy night monkey", "weight": 1}, {"mammal": "Large flying fox", "weight": 1}, {"mammal": "Chaco tuco-tuco", "weight": 1}, {"mammal": "Greater long-nosed bandicoot", "weight": 1}, {"mammal": "Ring-tailed possum", "weight": 1}, {"mammal": "Golden-bellied water rat", "weight": 1}, {"mammal": "Azara's opossum", "weight": 1}, {"mammal": "Leeser hairy armadillo", "weight": 1}, {"mammal": "European polecat", "weight": 1}, {"mammal": "Dusky titi", "weight": 1}, {"mammal": "Javan mongoose", "weight": 1}, {"mammal": "Northern night monkey", "weight": 1}, {"mammal": "Malagasy ring-tailed mongoose", "weight": 1}, {"mammal": "Eastern fox squirrel", "weight": 1}, {"mammal": "Bolivian titi", "weight": 1}, {"mammal": "Long-nosed cusimanse", "weight": 1}, {"mammal": "Central American squirrel monkey", "weight": 1}, {"mammal": "Red-tailed sportive lemur", "weight": 1}, {"mammal": "Meerkat", "weight": 1}, {"mammal": "Spectacled flying fox", "weight": 1}, {"mammal": "Acouchi", "weight": 1}, {"mammal": "Long-nosed bandicoot", "weight": 1}, {"mammal": "Nuttall's cottontail rabbit", "weight": 1}, {"mammal": "Crested rat", "weight": 1}, {"mammal": "Western European hedgehog", "weight": 1}, {"mammal": "Algerian hedgehog", "weight": 1}, {"mammal": "Guinea pig", "weight": 1}, {"mammal": "Eastern European hedgehog", "weight": 1}, {"mammal": "Abert's squirrel", "weight": 1}, {"mammal": "Water opossum (yapok)", "weight": 1}, {"mammal": "Southern brown bandicoot", "weight": 1}, {"mammal": "Weasel sportive lemur", "weight": 1}, {"mammal": "Banded linsang", "weight": 1}, {"mammal": "Brush rabbit", "weight": 1}, {"mammal": "Narrow-striped mongoose", "weight": 1}, {"mammal": "Comoro black flying fox", "weight": 1}, {"mammal": "Gray-headed flying fox", "weight": 1}, {"mammal": "New Guinean bandicoot", "weight": 1}, {"mammal": "Black flying fox", "weight": 1}, {"mammal": "Ferret badger", "weight": 1}, {"mammal": "Rock squirrel", "weight": 1}, {"mammal": "Bahamian hutia", "weight": 1}, {"mammal": "Golden lion tamarin", "weight": 1}, {"mammal": "New Guinea spiny bandicoot", "weight": 1}, {"mammal": "Cape grey mongoose", "weight": 1}, {"mammal": "Lesser bamboo rat", "weight": 1}, {"mammal": "Chinchilla", "weight": 1}, {"mammal": "Peruvian guinea pig", "weight": 1}, {"mammal": "Bolivian squirrel monkey", "weight": 1}, {"mammal": "African pygmy (four-toed) hedgehog", "weight": 1}, {"mammal": "Spotted skunk", "weight": 1}, {"mammal": "Eurasian red squirrel", "weight": 1}, {"mammal": "Striped ground squirrel", "weight": 1}, {"mammal": "Red-bellied squirrel", "weight": 1}, {"mammal": "Yellow mongoose", "weight": 1}, {"mammal": "European mink", "weight": 1}, {"mammal": "South African ground squirrel", "weight": 1}, {"mammal": "Fluffy glider", "weight": 1}, {"mammal": "Golden-rumped lion tamarin", "weight": 1}, {"mammal": "Siberian weasel", "weight": 1}, {"mammal": "Goeldi's monkey", "weight": 1}, {"mammal": "Midas tamarin", "weight": 1}, {"mammal": "Black-chested mustached tamarin", "weight": 1}, {"mammal": "Marbled polecat", "weight": 1}, {"mammal": "Golden-rumped elephant shrew", "weight": 1}, {"mammal": "Golden-headed lion tamarin", "weight": 1}, {"mammal": "Eastern gray squirrel", "weight": 1}, {"mammal": "Pemba flying fox", "weight": 1}, {"mammal": "Northern quoll", "weight": 1}, {"mammal": "Black-mantled tamarin", "weight": 1}, {"mammal": "Emperor tamarin", "weight": 1}, {"mammal": "Black-bellied hamster", "weight": 1}, {"mammal": "Armored rat", "weight": 1}, {"mammal": "Red-chested mustached tamarin", "weight": 1}, {"mammal": "Spiny rat", "weight": 1}, {"mammal": "Musky rat kangaroo", "weight": 1}, {"mammal": "Slender mongoose", "weight": 1}, {"mammal": "Geoffroy's tamarin", "weight": 0}, {"mammal": "Brazilian bare-faced tamarin", "weight": 0}, {"mammal": "Silvery-brown bare-face tamarin", "weight": 0}, {"mammal": "Variegated squirrel", "weight": 0}, {"mammal": "Golden bandicoot", "weight": 0}, {"mammal": "Numbat", "weight": 0}, {"mammal": "Franklin's ground squirrel", "weight": 0}, {"mammal": "Saddlebacked tamarin", "weight": 0}, {"mammal": "Mauritius flying fox", "weight": 0}, {"mammal": "Yellow-toothed cavy", "weight": 0}, {"mammal": "Variable flying fox", "weight": 0}, {"mammal": "Gray four-eyed opossum", "weight": 0}, {"mammal": "Cotton-top tamarin", "weight": 0}, {"mammal": "Brown four-eyed opossum", "weight": 0}, {"mammal": "Ryukyu flying fox", "weight": 0}, {"mammal": "Guayaquil squirrel", "weight": 0}, {"mammal": "Moluccan naked-backed fruit bat", "weight": 0}, {"mammal": "Western gray squirrel", "weight": 0}, {"mammal": "Pygmy rabbit", "weight": 0}, {"mammal": "Pygmy loris", "weight": 0}, {"mammal": "Squirrel glider", "weight": 0}, {"mammal": "Barbary ground squirrel", "weight": 0}, {"mammal": "Quaira spiny rat", "weight": 0}, {"mammal": "Fork-marked lemur", "weight": 0}, {"mammal": "Prevost's squirrel", "weight": 0}, {"mammal": "Texas pocket gopher", "weight": 0}, {"mammal": "Greater dwarf lemur", "weight": 0}, {"mammal": "Fat-tailed dwarf lemur", "weight": 0}, {"mammal": "Brazilian spiny rat", "weight": 0}, {"mammal": "Red-tailed squirrel", "weight": 0}, {"mammal": "Thick-tailed opossum", "weight": 0}, {"mammal": "Checkered elephant shrew", "weight": 0}, {"mammal": "Cayenne spiny rat", "weight": 0}, {"mammal": "Philippine tree shrew", "weight": 0}, {"mammal": "Rodriguez flying fox", "weight": 0}, {"mammal": "Woolly opossum", "weight": 0}, {"mammal": "Great jerboa", "weight": 0}, {"mammal": "Richardson's ground squirrel", "weight": 0}, {"mammal": "Long-eared desert hedgehog", "weight": 0}, {"mammal": "Geoffroy's marmoset", "weight": 0}, {"mammal": "Weid's black-tufted-ear marmoset", "weight": 0}, {"mammal": "Brazilian guinea pig", "weight": 0}, {"mammal": "Common yellow-toothed cavy", "weight": 0}, {"mammal": "Bushy-tailed woodrat", "weight": 0}, {"mammal": "Mueller's giant Sunda rat", "weight": 0}, {"mammal": "Greater stick-nest rat", "weight": 0}, {"mammal": "Hammer-headed fruit bat", "weight": 0}, {"mammal": "Central American woolly opossum", "weight": 0}, {"mammal": "Red-legged sun squirrel", "weight": 0}, {"mammal": "Black four-eyed opossum", "weight": 0}, {"mammal": "Striped possum", "weight": 0}, {"mammal": "Lyle's flying fox", "weight": 0}, {"mammal": "Western needle-clawed galago", "weight": 0}, {"mammal": "Horse-tailed squirrel", "weight": 0}, {"mammal": "South African hedgehog", "weight": 0}, {"mammal": "Black-pencilled marmoset", "weight": 0}, {"mammal": "Straw-colored fruit bat", "weight": 0}, {"mammal": "Little red flying fox", "weight": 0}, {"mammal": "Norway rat", "weight": 0}, {"mammal": "Eastern woodrat", "weight": 0}, {"mammal": "Belding's ground squirrel", "weight": 0}, {"mammal": "Gundi", "weight": 0}, {"mammal": "Great gerbil", "weight": 0}, {"mammal": "Andean spiny rat", "weight": 0}, {"mammal": "White-naped weasel", "weight": 0}, {"mammal": "Peters's climbing rat", "weight": 0}, {"mammal": "Armored spiny rat", "weight": 0}, {"mammal": "Dwarf mongoose", "weight": 0}, {"mammal": "Cascade golden-mantled ground squirrel", "weight": 0}, {"mammal": "Allen's squirrel galago", "weight": 0}, {"mammal": "Pallas's squirrel", "weight": 0}, {"mammal": "Fire-footed rope squirrel", "weight": 0}, {"mammal": "Yellow-faced pocket gopher", "weight": 0}, {"mammal": "Golden-backed tree rat", "weight": 0}, {"mammal": "Silky anteater", "weight": 0}, {"mammal": "Chinchilla-rat", "weight": 0}, {"mammal": "Small pika", "weight": 0}, {"mammal": "Calabar angwantibo", "weight": 0}, {"mammal": "Gray-bellied squirrel", "weight": 0}, {"mammal": "White-tufted-ear marmoset", "weight": 0}, {"mammal": "Black-shouldered opossum", "weight": 0}, {"mammal": "Giant mole-rat", "weight": 0}, {"mammal": "Slender loris", "weight": 0}, {"mammal": "Desert woodrat", "weight": 0}, {"mammal": "Southern plains woodrat", "weight": 0}, {"mammal": "Degus", "weight": 0}, {"mammal": "Euphrates jerboa", "weight": 0}, {"mammal": "Shark Bay Islands barred bandicoot", "weight": 0}, {"mammal": "Greater hedgehog tenrec", "weight": 0}, {"mammal": "East African mole rat", "weight": 0}, {"mammal": "Thomas's rope squirrel", "weight": 0}, {"mammal": "European ground squirrel", "weight": 0}, {"mammal": "Smith's bush squirrel", "weight": 0}, {"mammal": "Fat sand rat", "weight": 0}, {"mammal": "Four-toed elephant shrew", "weight": 0}, {"mammal": "White-throated woodrat", "weight": 0}, {"mammal": "Tree shrew", "weight": 0}, {"mammal": "Red squirrel", "weight": 0}, {"mammal": "Northern tree shrew", "weight": 0}, {"mammal": "Dassie rat", "weight": 0}, {"mammal": "Little golden-mantled flying fox", "weight": 0}, {"mammal": "Rat", "weight": 0}, {"mammal": "Large tree shrew", "weight": 0}, {"mammal": "Tuan", "weight": 0}, {"mammal": "Senegal galago", "weight": 0}, {"mammal": "Deppe's squirrel", "weight": 0}, {"mammal": "Bolivian squirrel", "weight": 0}, {"mammal": "Plantain squirrel", "weight": 0}, {"mammal": "Kintampo rope squirrel", "weight": 0}, {"mammal": "Guianan squirrel", "weight": 0}, {"mammal": "Hispid cotton rat", "weight": 0}, {"mammal": "Shaw's jird", "weight": 0}, {"mammal": "Cape mole-rat", "weight": 0}, {"mammal": "Lesser hedgehog tenrec", "weight": 0}, {"mammal": "Streaked tenrec", "weight": 0}, {"mammal": "Damaraland mole-rat", "weight": 0}, {"mammal": "Speke's gundi", "weight": 0}, {"mammal": "Plains pocket gopher", "weight": 0}, {"mammal": "Gray tree rat", "weight": 0}, {"mammal": "Three-striped ground squirrel", "weight": 0}, {"mammal": "South African galago", "weight": 0}, {"mammal": "Brandt's hamster", "weight": 0}, {"mammal": "Orange-bellied Himalayan squirrel", "weight": 0}, {"mammal": "Thirteen-lined ground squirrel", "weight": 0}, {"mammal": "Round-tailed ground squirrel", "weight": 0}, {"mammal": "Palestine mole rat", "weight": 0}, {"mammal": "Silvery mole-rat", "weight": 0}, {"mammal": "Chozchoz", "weight": 0}, {"mammal": "Golden-mantled ground squirrel", "weight": 0}, {"mammal": "Nelson's antelope squirrel", "weight": 0}, {"mammal": "Long-tailed weasel", "weight": 0}, {"mammal": "Vinogradov's jird", "weight": 0}, {"mammal": "Australian false vampire bat", "weight": 0}, {"mammal": "Northern flying squirrel", "weight": 0}, {"mammal": "Northern palm squirrel", "weight": 0}, {"mammal": "Indian gerbil", "weight": 0}, {"mammal": "Vlei rat", "weight": 0}, {"mammal": "Spectral tarsier", "weight": 0}, {"mammal": "Banner-tailed kangaroo rat", "weight": 0}, {"mammal": "Brush-tailed rabbit rat", "weight": 0}, {"mammal": "Little ground squirrel", "weight": 0}, {"mammal": "Ear-spot squirrel", "weight": 0}, {"mammal": "Greater Egyptian jerboa", "weight": 0}, {"mammal": "Green bush squirrel", "weight": 0}, {"mammal": "African mole rat", "weight": 0}, {"mammal": "Bush rat", "weight": 0}, {"mammal": "Siberian flying squirrel", "weight": 0}, {"mammal": "Collared pika", "weight": 0}, {"mammal": "Leadbeater's possum", "weight": 0}, {"mammal": "Harris's antelope squirrel", "weight": 0}, {"mammal": "Carpentarian rock rat", "weight": 0}, {"mammal": "Western tarsier", "weight": 0}, {"mammal": "Asian garden dormouse", "weight": 0}, {"mammal": "European water vole", "weight": 0}, {"mammal": "Philippine tarsier", "weight": 0}, {"mammal": "Siberian five-toed jerboa", "weight": 0}, {"mammal": "Botta's pocket gopher", "weight": 0}, {"mammal": "Desert kangaroo rat", "weight": 0}, {"mammal": "Australian swamp rat", "weight": 0}, {"mammal": "Mulgara", "weight": 0}, {"mammal": "Savanna gerbil", "weight": 0}, {"mammal": "Nile kusu", "weight": 0}, {"mammal": "Sugar glider", "weight": 0}, {"mammal": "Ermine", "weight": 0}, {"mammal": "Leschenault's rousette", "weight": 0}, {"mammal": "Congo rope squirrel", "weight": 0}, {"mammal": "White-tailed mouse", "weight": 0}, {"mammal": "Golden hamster", "weight": 0}, {"mammal": "Shorttailed opossum", "weight": 0}, {"mammal": "White-tailed antelope squirrel", "weight": 0}, {"mammal": "Northern pocket gopher", "weight": 0}, {"mammal": "Long-haired rousette", "weight": 0}, {"mammal": "Libyan jird", "weight": 0}, {"mammal": "Central rock rat", "weight": 0}, {"mammal": "Persian jird", "weight": 0}, {"mammal": "Tuco-tuco", "weight": 0}, {"mammal": "Indian palm squirrel", "weight": 0}, {"mammal": "Mohave ground squirrel", "weight": 0}, {"mammal": "North American pika", "weight": 0}, {"mammal": "Coruro", "weight": 0}, {"mammal": "Eastern chipmunk", "weight": 0}, {"mammal": "European mole, common mole", "weight": 0}, {"mammal": "Ansell's mole-rat", "weight": 0}, {"mammal": "Eastern aquatic mole", "weight": 0}, {"mammal": "Short bare-tailed opossum", "weight": 0}, {"mammal": "Splendid climbing mouse", "weight": 0}, {"mammal": "Long-eared chipmunk", "weight": 0}, {"mammal": "Arctic lemming", "weight": 0}, {"mammal": "Siberian chipmunk", "weight": 0}, {"mammal": "Garden dormouse", "weight": 0}, {"mammal": "Greater spear-nosed bat", "weight": 0}, {"mammal": "Acacia rat", "weight": 0}, {"mammal": "Gambian epauletted fruit bat", "weight": 0}, {"mammal": "Wahlberg's epauletted fruit bat", "weight": 0}, {"mammal": "Malabar spiny dormouse", "weight": 0}, {"mammal": "Townsend's chipmunk", "weight": 0}, {"mammal": "Slender squirrel", "weight": 0}, {"mammal": "Greater short-nosed fruit bat", "weight": 0}, {"mammal": "Red-tailed chipmunk", "weight": 0}, {"mammal": "Western pocket gopher", "weight": 0}, {"mammal": "Robinson's mouse opossum", "weight": 0}, {"mammal": "Cape gerbil", "weight": 0}, {"mammal": "Bunny or coney rat", "weight": 0}, {"mammal": "Colorado chipmunk", "weight": 0}, {"mammal": "Speckled marsupial mouse", "weight": 0}, {"mammal": "Smoky mouse", "weight": 0}, {"mammal": "Norway lemming", "weight": 0}, {"mammal": "Sand-colored rat", "weight": 0}, {"mammal": "Greater bulldog bat", "weight": 0}, {"mammal": "Low's squirrel", "weight": 0}, {"mammal": "Collared lemming", "weight": 0}, {"mammal": "Australian native mouse", "weight": 0}, {"mammal": "Bushy-tailed jird", "weight": 0}, {"mammal": "Thicket rat", "weight": 0}, {"mammal": "Gray mouse lemur", "weight": 0}, {"mammal": "Heermann's kangaroo rat", "weight": 0}, {"mammal": "Great fruit-eating bat", "weight": 0}, {"mammal": "Lesser short-nosed fruit bat", "weight": 0}, {"mammal": "Southern flying squirrel", "weight": 0}, {"mammal": "Heath mouse", "weight": 0}, {"mammal": "Cretan spiny mouse", "weight": 0}, {"mammal": "Cliff chipmunk", "weight": 0}, {"mammal": "Hairy-tailed mole", "weight": 0}, {"mammal": "Agile kangaroo rat", "weight": 0}, {"mammal": "Long-tailed mouse", "weight": 0}, {"mammal": "Woodland mouse", "weight": 0}, {"mammal": "Five-toed jerboa", "weight": 0}, {"mammal": "Lesser tree shrew", "weight": 0}, {"mammal": "African water rat", "weight": 0}, {"mammal": "Tundra vole", "weight": 0}, {"mammal": "Pyrenean desman", "weight": 0}, {"mammal": "Rufous elephant shrew", "weight": 0}, {"mammal": "Ord's kangaroo rat", "weight": 0}, {"mammal": "Long-tailed tree mouse", "weight": 0}, {"mammal": "Brown mouse lemur", "weight": 0}, {"mammal": "South African broad-headed mouse", "weight": 0}, {"mammal": "Julia Creek dunnart", "weight": 0}, {"mammal": "Star-nosed mole", "weight": 0}, {"mammal": "Lesser Egyptian jerboa", "weight": 0}, {"mammal": "Richardson's collared lemming", "weight": 0}, {"mammal": "Cape short-eared gerbil", "weight": 0}, {"mammal": "Cinnamon antechinus", "weight": 0}, {"mammal": "Golden spiny mouse", "weight": 0}, {"mammal": "Marsupial mole", "weight": 0}, {"mammal": "Mid-day jird", "weight": 0}, {"mammal": "Mongolian jird", "weight": 0}, {"mammal": "Long-eared elephant shrew", "weight": 0}, {"mammal": "Feather-tailed possum", "weight": 0}, {"mammal": "Vole", "weight": 0}, {"mammal": "Mitchell's hopping mouse", "weight": 0}, {"mammal": "Slender gerbil", "weight": 0}, {"mammal": "Four-striped grass mouse", "weight": 0}, {"mammal": "Darwin's leaf-eared mouse", "weight": 0}, {"mammal": "Water vole", "weight": 0}, {"mammal": "Vesper rat", "weight": 0}, {"mammal": "Mexican mouse opossum", "weight": 0}, {"mammal": "Pale gerbil", "weight": 0}, {"mammal": "Talazaci's long-tailed tenrec", "weight": 0}, {"mammal": "Flat-headed vole", "weight": 0}, {"mammal": "Common rock rat", "weight": 0}, {"mammal": "Cape elephant shrew", "weight": 0}, {"mammal": "Meadow vole", "weight": 0}, {"mammal": "Yellow-pine chipmunk", "weight": 0}, {"mammal": "North African elephant shrew", "weight": 0}, {"mammal": "Rock mouse", "weight": 0}, {"mammal": "Common weasel", "weight": 0}, {"mammal": "Red-nosed mouse", "weight": 0}, {"mammal": "Pouched mouse", "weight": 0}, {"mammal": "Rock dormouse", "weight": 0}, {"mammal": "House shrew", "weight": 0}, {"mammal": "Field vole", "weight": 0}, {"mammal": "Greater red musk shrew", "weight": 0}, {"mammal": "Mountain pygmy possum", "weight": 0}, {"mammal": "Yellow-footed marsupial mouse", "weight": 0}, {"mammal": "Spiny mouse", "weight": 0}, {"mammal": "Short-nosed elephant shrew", "weight": 0}, {"mammal": "Least chipmunk", "weight": 0}, {"mammal": "Pink fairy armadillo", "weight": 0}, {"mammal": "Pen-tailed tree shrew", "weight": 0}, {"mammal": "Pale spear-nosed bat", "weight": 0}, {"mammal": "Red-tailed phascogale", "weight": 0}, {"mammal": "Panamanian spiny pocket mouse", "weight": 0}, {"mammal": "Typical striped grass mouse", "weight": 0}, {"mammal": "Merriam's kangaroo rat", "weight": 0}, {"mammal": "Jamaican fruit-eating bat", "weight": 0}, {"mammal": "California mouse", "weight": 0}, {"mammal": "Swamp antechinus", "weight": 0}, {"mammal": "Dusky antechinus", "weight": 0}, {"mammal": "Fat-tailed gerbil", "weight": 0}, {"mammal": "Prairie vole", "weight": 0}, {"mammal": "Guatemalan deer mouse", "weight": 0}, {"mammal": "Brandt's vole", "weight": 0}, {"mammal": "Dormouse possum", "weight": 0}, {"mammal": "Short-eared elephant shrew", "weight": 0}, {"mammal": "Greater false vampire bat", "weight": 0}, {"mammal": "Northern hopping mouse", "weight": 0}, {"mammal": "Dobson's long-tailed tenrec", "weight": 0}, {"mammal": "Silver mountain vole", "weight": 0}, {"mammal": "Guinea multimammate mouse", "weight": 0}, {"mammal": "Woolley's pseudantechinus", "weight": 0}, {"mammal": "Long-tailed vole", "weight": 0}, {"mammal": "Greater Egyptian gerbil", "weight": 0}, {"mammal": "Fresno kangaroo rat", "weight": 0}, {"mammal": "Australian hopping mouse", "weight": 0}, {"mammal": "European free-tailed bat", "weight": 0}, {"mammal": "Cloudy short-tailed opossum", "weight": 0}, {"mammal": "Sundevall's jird", "weight": 0}, {"mammal": "Naked mole-rat", "weight": 0}, {"mammal": "Fawn antechinus", "weight": 0}, {"mammal": "Red-cheeked dunnart", "weight": 0}, {"mammal": "Western heather vole", "weight": 0}, {"mammal": "Northern grasshopper mouse", "weight": 0}, {"mammal": "Fat-tailed marsupial mouse", "weight": 0}, {"mammal": "Korean field mouse", "weight": 0}, {"mammal": "Vampire bat", "weight": 0}, {"mammal": "Florida mouse", "weight": 0}, {"mammal": "Little red kaluta", "weight": 0}, {"mammal": "Long-tailed pygmy possum", "weight": 0}, {"mammal": "Grey red-backed vole", "weight": 0}, {"mammal": "Lesser Egyptian gerbil", "weight": 0}, {"mammal": "Tullberg's rock rat", "weight": 0}, {"mammal": "Yellow-necked mouse", "weight": 0}, {"mammal": "Pencil-tailed tree mouse", "weight": 0}, {"mammal": "Mouse-eared bat", "weight": 0}, {"mammal": "Sandstone marsupial mouse", "weight": 0}, {"mammal": "Noctule", "weight": 0}, {"mammal": "Brown antechinus", "weight": 0}, {"mammal": "Common vole", "weight": 0}, {"mammal": "Japanese dormouse", "weight": 0}, {"mammal": "Hazel dormouse", "weight": 0}, {"mammal": "Eastern heather vole", "weight": 0}, {"mammal": "Southern bog lemming", "weight": 0}, {"mammal": "Forest dormouse", "weight": 0}, {"mammal": "Murine mouse opossum", "weight": 0}, {"mammal": "Woodland vole", "weight": 0}, {"mammal": "Barbary striped grass mouse", "weight": 0}, {"mammal": "Fat mouse", "weight": 0}, {"mammal": "Cactus mouse", "weight": 0}, {"mammal": "Pinyon mouse", "weight": 0}, {"mammal": "Fish-eating bat", "weight": 0}, {"mammal": "Wood lemming", "weight": 0}, {"mammal": "Woodland jumping mouse", "weight": 0}, {"mammal": "Monito del monte", "weight": 0}, {"mammal": "New Zealand lesser short-tailed bat", "weight": 0}, {"mammal": "Woodland dormouse", "weight": 0}, {"mammal": "Hoary bat", "weight": 0}, {"mammal": "Kultarr", "weight": 0}, {"mammal": "Greater horseshoe bat", "weight": 0}, {"mammal": "Dzhungarian hamster", "weight": 0}, {"mammal": "Mediterranean pine vole", "weight": 0}, {"mammal": "Lesser mouse-eared bat", "weight": 0}, {"mammal": "White-footed mouse", "weight": 0}, {"mammal": "Big brown bat", "weight": 0}, {"mammal": "Old World wood and field mouse", "weight": 0}, {"mammal": "Striped field mouse", "weight": 0}, {"mammal": "White-lined broad-nosed bat", "weight": 0}, {"mammal": "Golden mouse", "weight": 0}, {"mammal": "Southern grasshopper mouse", "weight": 0}, {"mammal": "Short-tailed shrew", "weight": 0}, {"mammal": "Paraguayan slender mouse opossum", "weight": 0}, {"mammal": "Rio Napo mouse opossum", "weight": 0}, {"mammal": "Red-backed mouse", "weight": 0}, {"mammal": "Pallid bat", "weight": 0}, {"mammal": "Western jumping mouse", "weight": 0}, {"mammal": "House mouse", "weight": 0}, {"mammal": "Deer mouse", "weight": 0}, {"mammal": "Highland gerbil mouse", "weight": 0}, {"mammal": "Great Basin pocket mouse", "weight": 0}, {"mammal": "Mouse-like hamster", "weight": 0}, {"mammal": "Little yellow-shouldered bat", "weight": 0}, {"mammal": "European pine vole", "weight": 0}, {"mammal": "Afghan mouse-like hamster", "weight": 0}, {"mammal": "African spiny mouse", "weight": 0}, {"mammal": "Steppe lemming", "weight": 0}, {"mammal": "Stripe-faced dunnart", "weight": 0}, {"mammal": "Baluchistan gerbil", "weight": 0}, {"mammal": "San Diego pocket mouse", "weight": 0}, {"mammal": "Long-tailed pocket mouse", "weight": 0}, {"mammal": "Particolored bat", "weight": 0}, {"mammal": "Meadow jumping mouse", "weight": 0}, {"mammal": "Philippine pygmy fruit bat", "weight": 0}, {"mammal": "Fawn-colored mouse", "weight": 0}, {"mammal": "Serotine", "weight": 0}, {"mammal": "Ningbing pseudantechinus", "weight": 0}, {"mammal": "Gray-bellied dunnart", "weight": 0}, {"mammal": "Forest shrew", "weight": 0}, {"mammal": "Canyon mouse", "weight": 0}, {"mammal": "Lesser noctule", "weight": 0}, {"mammal": "Seba's short-tailed bat", "weight": 0}, {"mammal": "Elliot's short-tailed shrew", "weight": 0}, {"mammal": "Southern water shrew", "weight": 0}, {"mammal": "Pond bat", "weight": 0}, {"mammal": "Fat-tailed dunnart", "weight": 0}, {"mammal": "Geoffroy's tailless bat", "weight": 0}, {"mammal": "Eurasian water shrew", "weight": 0}, {"mammal": "Oldfield mouse", "weight": 0}, {"mammal": "Nelson's pocket mouse", "weight": 0}, {"mammal": "Townsend's big-eared bat", "weight": 0}, {"mammal": "Northern bat", "weight": 0}, {"mammal": "Brant's climbing mouse", "weight": 0}, {"mammal": "Pygmy gliding possum", "weight": 0}, {"mammal": "Dark kangaroo mouse", "weight": 0}, {"mammal": "Brazilian free-tailed bat", "weight": 0}, {"mammal": "Western pebble-mound mouse", "weight": 0}, {"mammal": "Arizona pocket mouse", "weight": 0}, {"mammal": "Kimberly mouse", "weight": 0}, {"mammal": "White-toothed shrew", "weight": 0}, {"mammal": "Western broad-nosed bat", "weight": 0}, {"mammal": "Little long-tailed dunnart", "weight": 0}, {"mammal": "Water shrew", "weight": 0}, {"mammal": "Gray big-eared bat", "weight": 0}, {"mammal": "California leaf-nosed bat", "weight": 0}, {"mammal": "Ryukyu mouse", "weight": 0}, {"mammal": "Ooldea dunnart", "weight": 0}, {"mammal": "Rafinesque's big-eared bat", "weight": 0}, {"mammal": "Bicolored white-toothed shrew", "weight": 0}, {"mammal": "Bechstein's bat", "weight": 0}, {"mammal": "Western harvest mouse", "weight": 0}, {"mammal": "Geoffroy's bat", "weight": 0}, {"mammal": "Pilbara ningaui", "weight": 0}, {"mammal": "Alston's brown mouse", "weight": 0}, {"mammal": "Nathusius's pipistrelle", "weight": 0}, {"mammal": "Cave myotis", "weight": 0}, {"mammal": "Pallas's long-tongued bat", "weight": 0}, {"mammal": "Little brown bat", "weight": 0}, {"mammal": "Silver-haired bat", "weight": 0}, {"mammal": "Crowned shrew", "weight": 0}, {"mammal": "Western barbastelle", "weight": 0}, {"mammal": "Pygmy planigale", "weight": 0}, {"mammal": "Lesser hairy-footed dunnart", "weight": 0}, {"mammal": "Evening bat", "weight": 0}, {"mammal": "Smaller horseshoe bat", "weight": 0}, {"mammal": "Honey possum", "weight": 0}, {"mammal": "Plains pocket mouse", "weight": 0}, {"mammal": "Wongai ningaui", "weight": 0}, {"mammal": "Gray myotis", "weight": 0}, {"mammal": "Southern free-tailed bat", "weight": 0}, {"mammal": "Eurasian shrew", "weight": 0}, {"mammal": "Northern birch mouse", "weight": 0}, {"mammal": "Arctic shrew", "weight": 0}, {"mammal": "Merriam's pocket mouse", "weight": 0}, {"mammal": "Brown big-eared bat", "weight": 0}, {"mammal": "Natterer's bat", "weight": 0}, {"mammal": "Northern pygmy mouse", "weight": 0}, {"mammal": "Eastern pipistrelle", "weight": 0}, {"mammal": "Silky pocket mouse", "weight": 0}, {"mammal": "Alpine shrew", "weight": 0}, {"mammal": "Indiana bat", "weight": 0}, {"mammal": "Smoky shrew", "weight": 0}, {"mammal": "Lesser shrew", "weight": 0}, {"mammal": "Trowbridge's shrew", "weight": 0}, {"mammal": "Little pocket mouse", "weight": 0}, {"mammal": "Greater sac-winged bat", "weight": 0}, {"mammal": "Western long-eared myotis", "weight": 0}, {"mammal": "Paucident planigale", "weight": 0}, {"mammal": "Large-eared tenrec", "weight": 0}, {"mammal": "Vagrant shrew", "weight": 0}, {"mammal": "Gray climbing mouse", "weight": 0}, {"mammal": "Keen's myotis", "weight": 0}, {"mammal": "Mouse", "weight": 0}, {"mammal": "Long-legged myotis", "weight": 0}, {"mammal": "Eurasian pygmy shrew", "weight": 0}, {"mammal": "Fulvus roundleaf bat", "weight": 0}, {"mammal": "Brandt's bat", "weight": 0}, {"mammal": "Yuma myotis", "weight": 0}, {"mammal": "Eastern small-footed myotis", "weight": 0}, {"mammal": "Montane shrew", "weight": 0}, {"mammal": "Ornate shrew", "weight": 0}, {"mammal": "Old World harvest mouse", "weight": 0}, {"mammal": "Kuhl's pipistrelle", "weight": 0}, {"mammal": "Fringed myotis", "weight": 0}, {"mammal": "Whiskered bat", "weight": 0}, {"mammal": "Laxmann's shrew", "weight": 0}, {"mammal": "Common pipistrelle", "weight": 0}, {"mammal": "Lesser horseshoe bat", "weight": 0}, {"mammal": "Least shrew", "weight": 0}, {"mammal": "Narrow-nosed planigale", "weight": 0}, {"mammal": "Long-tailed planigale", "weight": 0}, {"mammal": "Cinereus shrew", "weight": 0}, {"mammal": "Black myotis", "weight": 0}, {"mammal": "White-toothed pygmy shrew", "weight": 0}]